receptiviti/__about__.py
receptiviti/__init__.py
receptiviti/frameworks.py
receptiviti/manage_request.py
receptiviti/norming.py
receptiviti/readin_env.py
receptiviti/request.py
receptiviti/status.py
receptiviti-0.2.2.dist-info/METADATA
receptiviti-0.2.2.dist-info/WHEEL
receptiviti-0.2.2.dist-info/licenses/LICENSE.txt
receptiviti-0.2.2.dist-info/RECORD
