Metadata-Version: 2.4
Name: receptiviti
Version: 0.2.2
Summary: Process texts with the Receptiviti API
Project-URL: Documentation, https://receptiviti.github.io/receptiviti-python
Project-URL: Release Notes, https://receptiviti.github.io/receptiviti-python/CHANGELOG
Project-URL: Issues, https://github.com/receptiviti/receptiviti-python/issues
Project-URL: Source, https://github.com/receptiviti/receptiviti-python
Author-email: Micah <micah.iserman@gmail.com>
License-Expression: MIT
License-File: LICENSE.txt
Classifier: Development Status :: 4 - Beta
Classifier: Programming Language :: Python
Classifier: Programming Language :: Python :: 3.8
Classifier: Programming Language :: Python :: 3.9
Classifier: Programming Language :: Python :: 3.10
Classifier: Programming Language :: Python :: 3.11
Classifier: Programming Language :: Python :: 3.12
Classifier: Programming Language :: Python :: 3.13
Classifier: Topic :: Scientific/Engineering
Requires-Python: >=3.8
Requires-Dist: chardet
Requires-Dist: numpy
Requires-Dist: pandas
Requires-Dist: pyarrow
Requires-Dist: requests
Requires-Dist: tqdm
Provides-Extra: dev
Requires-Dist: mkdocs-material>=9.1.15; extra == 'dev'
Requires-Dist: mkdocs>=1.4.3; extra == 'dev'
Requires-Dist: mkdocstrings[python]>=0.18; extra == 'dev'
Requires-Dist: pyarrow-stubs; extra == 'dev'
Requires-Dist: types-requests; extra == 'dev'
